horizonplot/__init__.py
horizonplot-2.0.1.dist-info/LICENSE
horizonplot-2.0.1.dist-info/METADATA
horizonplot-2.0.1.dist-info/WHEEL
horizonplot-2.0.1.dist-info/top_level.txt
horizonplot-2.0.1.dist-info/RECORD
