Metadata-Version: 2.1
Name: horizonplot
Version: 2.0.1
Summary: Generates horizon plots.
Home-page: https://github.com/kaspermunch/horizonplot
Author: Kasper Munch
Requires-Python: >=3.6
License-File: LICENSE
Requires-Dist: pandas >=1.0
Requires-Dist: numpy >=1.1
Requires-Dist: seaborn >=0.1
Requires-Dist: matplotlib >=3.0
